cerami/__init__.py
cerami/model.py
cerami/data_attribute/__init__.py
cerami/data_attribute/dynamo_data_attribute.py
cerami/data_attribute/dynamo_data_list_attribute.py
cerami/data_attribute/dynamo_data_scalar_attribute.py
cerami/datatype/__init__.py
cerami/datatype/base_datatype.py
cerami/datatype/base_number.py
cerami/datatype/base_string.py
cerami/datatype/boolean.py
cerami/datatype/byte_buffer.py
cerami/datatype/datetime.py
cerami/datatype/dynamic.py
cerami/datatype/model_map.py
cerami/datatype/number.py
cerami/datatype/set.py
cerami/datatype/string.py
cerami/datatype/uniform_list.py
cerami/datatype/expression/__init__.py
cerami/datatype/expression/arithmetic_expression.py
cerami/datatype/expression/base_expression.py
cerami/datatype/expression/begins_with_expression.py
cerami/datatype/expression/between_expression.py
cerami/datatype/expression/contains_expression.py
cerami/datatype/expression/equality_expression.py
cerami/datatype/expression/in_expression.py
cerami/datatype/expression/list_append_expression.py
cerami/datatype/expression/update_remove_expression.py
cerami/datatype/translator/__init__.py
cerami/datatype/translator/base_datatype_translator.py
cerami/datatype/translator/boolean_translator.py
cerami/datatype/translator/byte_translator.py
cerami/datatype/translator/datetime_translator.py
cerami/datatype/translator/decimal_translator.py
cerami/datatype/translator/dict_translator.py
cerami/datatype/translator/integer_translator.py
cerami/datatype/translator/list_translator.py
cerami/datatype/translator/model_translator.py
cerami/datatype/translator/set_translator.py
cerami/datatype/translator/string_translator.py
cerami/datatype/translator/uniform_list_translator.py
cerami/decorators/__init__.py
cerami/decorators/primary_key.py
cerami/reconstructor/__init__.py
cerami/reconstructor/base_reconstructor.py
cerami/reconstructor/model_reconstructor.py
cerami/reconstructor/raw_reconstructor.py
cerami/request/__init__.py
cerami/request/delete_request.py
cerami-0.3.8.dist-info/LICENSE
cerami-0.3.8.dist-info/METADATA
cerami-0.3.8.dist-info/WHEEL
cerami-0.3.8.dist-info/top_level.txt
cerami-0.3.8.dist-info/RECORD
