Metadata-Version: 2.1
Name: cerami
Version: 0.3.8
Summary: A Dynamodb ORM
Home-page: https://github.com/gummybuns/cerami
Author: Zac Brown
Author-email: gummybuns@protonmail.com
License: UNKNOWN
Platform: UNKNOWN
Classifier: Programming Language :: Python :: 3
Classifier: License :: OSI Approved :: MIT License
Classifier: Operating System :: OS Independent
Requires-Python: >=3.6
License-File: LICENSE
Requires-Dist: boto3
Requires-Dist: python-dateutil
